raspreboot/__init__.py
raspreboot/reboot.py
raspreboot-0.0.6.dist-info/LICENSE
raspreboot-0.0.6.dist-info/METADATA
raspreboot-0.0.6.dist-info/WHEEL
raspreboot-0.0.6.dist-info/top_level.txt
raspreboot-0.0.6.dist-info/RECORD
