Metadata-Version: 2.1
Name: raspreboot
Version: 0.0.6
Summary: This package will take care of rebooting rasp in case internet is offline.
Author: Shivam Sharma
Author-email: shivamsharma1913@gmail.com
License-File: LICENSE
Requires-Dist: setuptools
Requires-Dist: wheel
Requires-Dist: ShynaTime
Requires-Dist: Shyna-speaks
